.gitignore
.travis.yml
MANIFEST.in
README.rst
bootstrap.py
setup.py
sphinx.cfg
sphinx_requirements.txt
travis.cfg
docs/CONTRIBUTORS.txt
docs/HISTORY.txt
docs/INSTALL.txt
docs/LICENSE.GPL
docs/LICENSE.txt
docs/api.rst
docs/conf.py
docs/index.rst
src/collective/__init__.py
src/collective.geo.geographer.egg-info/PKG-INFO
src/collective.geo.geographer.egg-info/SOURCES.txt
src/collective.geo.geographer.egg-info/dependency_links.txt
src/collective.geo.geographer.egg-info/entry_points.txt
src/collective.geo.geographer.egg-info/namespace_packages.txt
src/collective.geo.geographer.egg-info/not-zip-safe
src/collective.geo.geographer.egg-info/requires.txt
src/collective.geo.geographer.egg-info/top_level.txt
src/collective/geo/__init__.py
src/collective/geo/geographer/README.rst
src/collective/geo/geographer/__init__.py
src/collective/geo/geographer/configure.zcml
src/collective/geo/geographer/event.py
src/collective/geo/geographer/geo.py
src/collective/geo/geographer/geoview.py
src/collective/geo/geographer/interfaces.py
src/collective/geo/geographer/testing.py
src/collective/geo/geographer/testing.zcml
src/collective/geo/geographer/profiles/default/catalog.xml
src/collective/geo/geographer/profiles/default/metadata.xml
src/collective/geo/geographer/tests/__init__.py
src/collective/geo/geographer/tests/test_doctests.py
src/collective/geo/geographer/tests/test_permissions.py
src/collective/geo/geographer/tests/test_setup.py