Metadata-Version: 1.1
Name: collective.geo.geographer
Version: 2.0
Summary: Geographic annotation for Plone
Home-page: http://plone.org/products/collective.geo
Author: Giorgio Borelli
Author-email: giorgio@giorgioborelli.it
License: GPL
Keywords: Zope Plone GIS KML Google Maps Bing OpenLayers
Platform: UNKNOWN
Classifier: Framework :: Plone
Classifier: Topic :: Internet
Classifier: Topic :: Scientific/Engineering :: GIS
Classifier: Programming Language :: Python
